setup.py
btcturk_client/__init__.py
btcturk_client/client.py
btcturk_client/tools.py
btcturk_client.egg-info/PKG-INFO
btcturk_client.egg-info/SOURCES.txt
btcturk_client.egg-info/dependency_links.txt
btcturk_client.egg-info/pbr.json
btcturk_client.egg-info/requires.txt
btcturk_client.egg-info/top_level.txt