Metadata-Version: 1.1
Name: btcturk-client
Version: 0.0.2
Summary: Btcturk.com api client
Home-page: https://github.com/emre/btcturk-client
Author: Emre Yilmaz
Author-email: mail@emreyilmaz.me
License: MIT
Platform: UNKNOWN
Classifier: Programming Language :: Python
Classifier: Programming Language :: Python :: 2.7
